debug_toolbar_sqlalchemy/__init__.py
debug_toolbar_sqlalchemy/operation_tracker.py
debug_toolbar_sqlalchemy/panel.py
debug_toolbar_sqlalchemy/templates/sqlalchemy-panel.html
django_debug_toolbar_sqlalchemy-0.3.0.dist-info/LICENSE
django_debug_toolbar_sqlalchemy-0.3.0.dist-info/METADATA
django_debug_toolbar_sqlalchemy-0.3.0.dist-info/WHEEL
django_debug_toolbar_sqlalchemy-0.3.0.dist-info/top_level.txt
django_debug_toolbar_sqlalchemy-0.3.0.dist-info/RECORD
