Metadata-Version: 2.1
Name: django-debug-toolbar-sqlalchemy
Version: 0.3.0
Summary: SQLAlchemy query information panel for Django Debug Toolbar
Home-page: https://github.com/kevinoconnor7/django-debug-toolbar-sqlalchemy
Author: Kevin O'Connor
Author-email: kevin@oconnor.mp
License: GPLv3
Platform: UNKNOWN
Classifier: Development Status :: 4 - Beta
Classifier: Environment :: Web Environment
Classifier: Framework :: Django
Classifier: Intended Audience :: Developers
Classifier: License :: OSI Approved :: GNU General Public License v3 (GPLv3)
Classifier: Operating System :: OS Independent
Classifier: Programming Language :: Python
Classifier: Topic :: Database
Classifier: Topic :: Software Development :: Libraries :: Python Modules
